pxr/.libs/libPxrArch.so
pxr_arch-25.5.1.dist-info/METADATA
pxr_arch-25.5.1.dist-info/WHEEL
pxr_arch-25.5.1.dist-info/RECORD
pxr_arch-25.5.1.dist-info/licenses/LICENSE.txt
pxr_arch-25.5.1.dist-info/licenses/NOTICE.txt
