Metadata-Version: 2.4
Name: pxr-arch
Version: 25.5.1
Summary: Architecture-dependent code used in OpenUSD
Keywords: pixar,open-usd
License-File: LICENSE.txt
License-File: NOTICE.txt
Classifier: Programming Language :: Python :: 3
Classifier: Operating System :: POSIX :: Linux
Classifier: Operating System :: MacOS :: MacOS X
Classifier: Operating System :: Microsoft :: Windows :: Windows 10
Project-URL: Repository, https://github.com/untwine/pxr-arch
Project-URL: Documentation, https://untwine.github.io/pxr-arch/
Requires-Python: >=3.8
